autologie/__init__.py
autologie/agents/agent_configs.py
autologie/interface/__init__.py
autologie/interface/interface.py
autologie/interface/streamlit_interface.py
autologie/llms/__init__.py
autologie/llms/clients.py
autologie/llms/inference_logger.py
autologie/llms/llms.py
autologie/llms/prompt_assets/coder_sys_prompt.yml
autologie/llms/prompt_assets/few_shot.json
autologie/llms/prompt_assets/sys_prompt.yml
autologie/llms/prompt_assets/web_search_sys_prompt.yml
autologie/llms/prompt_handlers.py
autologie/llms/response_handlers.py
autologie/llms/types/__init__.py
autologie/llms/types/chat_templates/chatml.j2
autologie/llms/types/chat_templates/vicuna.j2
autologie/llms/types/chat_templates/zephyr.j2
autologie/llms/types/generation_settings.py
autologie/llms/types/helpers/gbnf_grammar_from_pydantic_models.py
autologie/llms/types/helpers/schema_generator.py
autologie/llms/types/messages.py
autologie/llms/types/payloads.py
autologie/llms/types/prompts.py
autologie/llms/types/responses.py
autologie/llms/types/types.py
autologie/llms/utils.py
autologie/memory/db.py
autologie/tools/nous_functions.py
autologie/tools/objects.py
autologie-0.1.0.dist-info/LICENSE
autologie-0.1.0.dist-info/METADATA
autologie-0.1.0.dist-info/WHEEL
autologie-0.1.0.dist-info/RECORD
